TP2/src/multiplication/delay_gen.vhd
library ieee;
use ieee.std_logic_1164.all;

entity delay_gen is
    generic(
            N: natural:= 26;
            DELAY: natural:= 0
        );
    port(
        clk: in std_logic;
        rst: in std_logic;
        A: in std_logic_vector(N-1 downto 0);
        B: out std_logic_vector(N-1 downto 0)
    );
end;


architecture behavioral of delay_gen is
    type std_logic_matrix is array(DELAY-1 downto 0) of std_logic_vector(N-1 downto 0);   
    signal sr : std_logic_matrix;
begin
    process(clk,rst)
    begin
        if rst='1' then
            sr <= (others=>(others=>'0'));
        elsif clk = '1' and clk'event then
            sr(DELAY-1 downto 1) <= sr(DELAY-2 downto 0);
            sr(0) <= A;
        end if;
    end process;
    B <= sr(DELAY-1);
end;

TP2/src/adder/register.vhd
library IEEE;
use IEEE.std_logic_1164.all;

entity reg is
    generic(N: integer := 4);
    port (
        clk : in std_logic;
        rst : in std_logic;
        ena : in std_logic;
        D : in std_logic_vector(N-1 downto 0);
        Q : out std_logic_vector(N-1 downto 0)
    );
end;

architecture behavioral of reg is
begin
    process(clk, rst)
    begin
        if rst='1' then
            Q <= (others => '0');
        elsif rising_edge(clk) then
            if ena='1' then
                Q <= D;
            end if;
        end if;
    end process;
end;

TP2/src/adder/fp_add.vhd
library IEEE;
use IEEE.std_logic_1164.all;
use IEEE.numeric_std.all;

entity fp_add is
    generic (
        NE : natural := 7;
        NF : natural := 21
    );
    port (
        clk : in std_logic;
        rst : in std_logic;
        add_sub : in std_logic;
        x : in std_logic_vector(NF+NE downto 0);
        y : in std_logic_vector(NF+NE downto 0);
        z : out std_logic_vector(NF+NE downto 0)
    );
end;

architecture behavioral of fp_add is
    function search_implicit_1(value: unsigned(2**NE+NF downto 0)) return integer is
        variable found : boolean := false;
        variable ind : integer range 0 to 2**NE+NF := 0;

    begin
        for i in (2**NE + NF) downto 0 loop
            if not found then 
                ind := i;
            end if;
            if value(i) = '1' then
                found := true;
            end if;
        end loop;

        return ind;
    end;


    signal is_0 : std_logic_vector(1 downto 0) := "00";
    signal saturation : std_logic_vector(1 downto 0) := "00";

    signal x_reg : std_logic_vector(NF+NE downto 0) := (others => '0');
    signal y_reg : std_logic_vector(NF+NE downto 0) := (others => '0');
    signal z_reg : std_logic_vector(NF+NE downto 0) := (others => '0');

    signal Sx : std_logic := '0';
    signal Fx : std_logic_vector(NF-1 downto 0) := (others => '0');
    signal Ex : std_logic_vector(NE-1 downto 0) := (others => '0');

    signal Sy : std_logic := '0';
    signal Fy : std_logic_vector(NF-1 downto 0) := (others => '0');
    signal Ey : std_logic_vector(NE-1 downto 0) := (others => '0');

    signal Sz : std_logic := '0';
    signal Fz : std_logic_vector(NF-1 downto 0) := (others => '0');
    signal Ez : std_logic_vector(NE-1 downto 0) := (others => '0');

    -- constantes y seniales del calculo del significante
    constant F_SAT_VALUE : std_logic_vector(NF-1 downto 0) := std_logic_vector(to_unsigned(2**NF-1, NF));
    constant F_ZERO_VALUE : std_logic_vector(NF-1 downto 0) := std_logic_vector(to_unsigned(0, NF));
    constant E_SAT_VALUE : std_logic_vector(NE-1 downto 0) := std_logic_vector(to_unsigned(2**NE-1, NE));
    constant E_ZERO_VALUE : std_logic_vector(NE-1 downto 0) := std_logic_vector(to_unsigned(0, NE));


    signal Fx_ext : unsigned(NF downto 0) := (others => '0');
    signal Fy_ext : unsigned(NF downto 0) := (others => '0');
    
    signal aligned_Fx : unsigned(NF+2**NE-1 downto 0) := (others => '0');
    signal aligned_Fy : unsigned(NF+2**NE-1 downto 0) := (others => '0');

    signal Mx : unsigned(NF+2**NE+1 downto 0) := (others => '0');
    signal My : unsigned(NF+2**NE+1 downto 0) := (others => '0');

    signal Sx_ext : std_logic := '0';
    signal Sy_ext : std_logic := '0';

    signal Mz_pre : unsigned(NF+2**NE+1 downto 0) := (others => '0');
    signal Mz : unsigned(NF+2**NE+1 downto 0) := (others => '0'); 
    signal Mz_shift : unsigned(NF+2**NE+1 downto 0) := (others => '0');
    signal Fz_pre : unsigned(NF-1 downto 0) := (others => '0');
    signal Fz_aux : std_logic_vector(NF-1 downto 0) := (others => '0');

    signal abs_exp_diff : unsigned(NE downto 0) := (others => '0');
    signal aux_index : integer range 0 to 2**NE+NF := 0;
    signal shift : integer := 0;
    signal lower_index : integer range 0 to 2**NE+NF := 20;
    signal upper_index : integer range 0 to 2**NE+NF := 0;


    -- constantes y seniales del calculo del exponente

    signal Ex_ext : unsigned(NE+1 downto 0);
    signal Ey_ext : unsigned(NE+1 downto 0);
    signal Ez_pre : unsigned(NE+1 downto 0);
    signal aux_Ez : std_logic_vector(NE-1 downto 0); 

    signal exp_diff : unsigned(NE+1 downto 0);
    signal index : unsigned(NE+1 downto 0);

begin

    regX: entity work.reg(behavioral)
            generic map(NF+NE+1)
            port map(
                clk => clk,
                rst => rst,
                ena => '1',
                D => x,
                Q => x_reg
            );

    regY: entity work.reg(behavioral)
            generic map (NF+NE+1)
            port map (
                clk => clk,
                rst => rst,
                ena => '1',
                D => y,
                Q => y_reg
            );

    regZ: entity work.reg(behavioral)
            generic map (NF+NE+1)
            port map (
                clk => clk,
                rst => rst,
                ena => '1',
                D => z_reg,
                Q => z
            );
    
    ZERO : is_0 <= "10" when (unsigned(x_reg(NF+NE-1 downto 0))=0 AND unsigned(y_reg(NF+NE-1 downto 0)) /=0) else
                   "10" when (unsigned(x_reg(NF+NE-1 downto 0))/=0 AND unsigned(y_reg(NF+NE-1 downto 0)) =0) else
                   "11" when (unsigned(x_reg(NF+NE-1 downto 0))=0 AND unsigned(y_reg(NF+NE-1 downto 0)) =0) else
                   "00";
    
    EXPONENT :
        Ex <= x_reg(NF+NE-1 downto NF);
        Ey <= y_reg(NF+NE-1 downto NF);

        Ex_ext <= "00" & unsigned(Ex);
        EY_ext <= "00" & unsigned(Ey);

        exp_diff <= Ex_ext + (not Ey_ext + 1);
        index <= unsigned(std_logic_vector(to_signed(shift, NE+2)));

        Ez_pre <= Ex_ext+index when exp_diff(NE)='0' else Ey_ext+index;

        -- chequeo por algun operando = 0;
        aux_Ez <= std_logic_vector(Ez_pre(NE-1 downto 0)) when is_0="00" else
                  Ex when is_0="01" else
                  Ey when is_0="10" else
                  E_ZERO_VALUE;

        -- saturacion
        saturation <= std_logic_vector(Ez_pre(NE+1 downto NE));
        Ez <= aux_Ez when (saturation="00" or saturation="10") else
              E_SAT_VALUE when (saturation="01") else
              E_ZERO_VALUE when (saturation="10");

    SIGNIFICAND : 

        -- tomo el significando de X y de Y
        Fx <= x_reg(NF-1 downto 0);
        Fy <= y_reg(NF-1 downto 0);

        -- elijo Fx* y Fy* segun el MSB de la resta de los exponentes y agrego el 1 implicito
        Fx_ext <= ('1' & unsigned(Fx)) when exp_diff(NE) = '0' else ('1' & unsigned(Fy));
        Fy_ext <= ('1' & unsigned(Fy)) when exp_diff(NE) = '0' else ('1' & unsigned(Fx));

        -- en caso de que la operacion sea una resta debo cambiar el signo del operando Y:
        Sx_ext <= Sx when exp_diff(NE) = '0' else (add_sub XOR Sy);
        Sy_ext <= add_sub XOR Sy when exp_diff(NE) = '0' else Sx;

        -- armo las alineaciones en funcion de la abs(Ex - Ey) 
        abs_exp_diff <= exp_diff(NE downto 0) when exp_diff(NE) = '0' else (not exp_diff(NE downto 0) + 1);
        aligned_Fy <= to_unsigned(0, 2**NE-1) & Fy_ext;
        aligned_Fx <= shift_left(to_unsigned(0, 2**NE-1) & Fx_ext, to_integer(abs_exp_diff));

        -- Complemento a 2 correspondiente a cada mantisa en funcion de su signo y si es una resta o una suma
        Mx <= "00" & unsigned(aligned_Fx) when Sx_ext='0' else ("11" & unsigned(not aligned_Fx + 1));
        My <= "00" & unsigned(aligned_Fy) when Sy_ext='0' else unsigned( "11" & not aligned_Fy + 1);

        -- Sumo ambas mantisas y si resulta negativa complemento.
        Mz_pre <=  Mx + My;
        Mz <= Mz_pre when (Mz_pre(2**NE+NF+1)='0') else (not Mz_pre+1);

        -- Busco el 1 implicito de la mantisa resultante
        aux_index <= search_implicit_1(Mz(2**NE+NF downto 0));
        shift <= aux_index - (NF+to_integer(abs_exp_diff));

        -- Defino los indices que corresponden al significando de Z (Fz),
        -- en caso de que el largo del vector resultante sea < NF, se paddea con 0 a la derecha.
        upper_index <= aux_index-1 when (aux_index>0) else 0;
        lower_index <= aux_index-NF when (aux_index-NF > 0) else 0;
        Mz_shift <= shift_left(Mz, Mz'length - aux_index);

        Fz_pre <= Mz_shift(Mz'length-1 downto Mz'length - NF);

        -- chequeo por algun operando = 0;
        Fz_aux <= std_logic_vector(Fz_pre) when (is_0="00") else
                  Fx when (is_0="01") else 
                  Fy when (is_0="10") else
                  F_ZERO_VALUE;

        -- saturacion
        Fz <= Fz_aux when (saturation="00" or saturation="10") else
        F_SAT_VALUE when (saturation="01") else
        F_ZERO_VALUE when (saturation="10");
    
    SIGN :  
        Sx <= x_reg(NF+NE);
        Sy <= y_reg(NF+NE);
        -- el signo de la salida es el signo de la mantisa resultante 
        -- (dado que complemente cada operando segun fuera necesario)
        Sz <= Mz_pre(2**NE+NF) when is_0="00" else
              Sx when is_0="01" else
              add_sub XOR Sy when is_0="10" else
              '0';

    z_reg <= Sz & Ez & Fz;
end;

TP2/src/adder/testbench_adder.vhd
library ieee;
use ieee.std_logic_1164.all;
use ieee.numeric_std.all;
use std.textio.all;


entity pf_testbench_add is
end entity pf_testbench_add;


architecture pf_testbench_add_arq of pf_testbench_add is
    constant TCK: time:= 20 ns; -- periodo de reloj
    constant DELAY: natural:= 2; -- retardo de procesamiento del DUV
    constant NF : natural := 21;
    constant EXP_SIZE_T: natural:= 7; -- tamanio exponente
    constant WORD_SIZE_T: natural:= NF+EXP_SIZE_T+1; -- tamanio de datos
    signal clk: std_logic := '0';
    signal rst: std_logic := '1';
    signal a_file: unsigned(WORD_SIZE_T-1 downto 0):= (others => '0');
    signal b_file: unsigned(WORD_SIZE_T-1 downto 0):= (others => '0');
    signal z_file: unsigned(WORD_SIZE_T-1 downto 0):= (others => '0');
    signal z_del: unsigned(WORD_SIZE_T-1 downto 0):= (others => '0'); 
    signal z_duv: std_logic_vector(WORD_SIZE_T-1 downto 0):= (others => '0');
    signal ciclos: integer := 0; signal errores: integer := 0;
    -- La senal z_del_aux se define por un problema de conversion
    signal z_del_aux: std_logic_vector(WORD_SIZE_T-1 downto 0):= (others => '0');

    signal add_sub : std_logic := '1';

    file datos: text open read_mode is "../testbench/fsub_21_7.txt";
    -- Declaracion del componente a probar
    component fp_add is
        generic(
                NE: natural := 8;
                NF: natural := 23
            );
            port(
                clk : in std_logic;
                rst : in std_logic;
                add_sub : in std_logic;
                x : in std_logic_vector(NF+NE downto 0);
                y : in std_logic_vector(NF+NE downto 0);
                z : out std_logic_vector(NF+NE downto 0)
                );
    end component fp_add ;
    -- Declaracion de la linea de retardo
    component delay_gen is
        generic(
            N: natural:= 26;
            DELAY: natural:= 0
        );
        port(
            clk: in std_logic;
            rst: in std_logic;
            A: in std_logic_vector(N-1 downto 0);
            B: out std_logic_vector(N-1 downto 0)
        );
    end component;
begin
    -- Generacion del clock del sistema
    clk <= not(clk) after TCK/ 2; -- reloj
    rst <= '0' after 1 ns;

    Test_Sequence: process
        variable l: line;

        variable ch: character:= ' ';
        variable aux: integer;
    begin
        while not(endfile(datos)) loop
            wait until rising_edge(clk);
            -- solo para debugging
            ciclos <= ciclos + 1;
            -- se lee una linea del archivo de valores de prueba
            readline(datos, l);
            -- se extrae un entero de la linea
            read(l, aux);
            -- se carga el valor del operando A
            a_file <= to_unsigned(aux, WORD_SIZE_T);
            -- se lee un caracter (es el espacio)
            read(l, ch);
            -- se lee otro entero de la linea
            read(l, aux);
            -- se carga el valor del operando B
            b_file <= to_unsigned(aux, WORD_SIZE_T);
            -- se lee otro caracter (es el espacio)
            read(l, ch);
            -- se lee otro entero
            read(l, aux);
            -- se carga el valor de salida (resultado)
            z_file <= to_unsigned(aux, WORD_SIZE_T);
        end loop;
        -- se cierra del archivo
        file_close(datos);
        wait for TCK*(DELAY+1);
        -- se aborta la simulacion (fin del archivo)
        assert false report
        "Fin de la simulacion" severity failure;
    end process Test_Sequence;
-- Instanciacion del DUV
DUV: fp_add 
        generic map (
                NE => EXP_SIZE_T,
                NF => NF
        )
        port map(
            clk => clk,
            rst => rst,
            add_sub => add_sub,
            x => std_logic_vector(a_file),
            y => std_logic_vector(b_file),
            z => z_duv
        );
-- Instanciacion de la linea de retardo
del: delay_gen
    generic map(WORD_SIZE_T, DELAY)
    port map(clk, '0', std_logic_vector(z_file), z_del_aux);
    z_del <= unsigned(z_del_aux);
-- Verificacion de la condicion
verificacion: process(clk)
        begin
            if rising_edge(clk) then
            assert to_integer(z_del) = to_integer(unsigned(z_duv)) report
            "Error: Salida del DUV no coincide con referencia (salida del duv = " &
            integer'image(to_integer(unsigned(z_duv))) & ", salida del archivo = " &
            integer'image(to_integer(z_del)) & ")" &
            "Errores= " & integer'image(errores+1) & " en la linea " & integer'image(ciclos-2)
            severity warning;
            if to_integer(z_del) /= to_integer(unsigned(z_duv)) then
            errores <= errores + 1;
            end if;
            end if;
        end process;
end architecture pf_testbench_add_arq;

TP2/sym/pf_testbench_add.vcd
$date
  Fri Nov 10 19:07:03 2023
$end
$version
  GHDL v0
$end
$timescale
  1 fs
$end
$scope module standard $end
$upscope $end
$scope module std_logic_1164 $end
$upscope $end
$scope module numeric_std $end
$upscope $end
$scope module textio $end
$upscope $end
$scope module pf_testbench_add $end
$var reg 1 ! clk $end
$var reg 1 " rst $end
$var reg 29 # a_file[28:0] $end
$var reg 29 $ b_file[28:0] $end
$var reg 29 % z_file[28:0] $end
$var reg 29 & z_del[28:0] $end
$var reg 29 ' z_duv[28:0] $end
$var integer 32 ( ciclos $end
$var integer 32 ) errores $end
$var reg 29 * z_del_aux[28:0] $end
$var reg 1 + add_sub $end
$scope module duv $end
$var reg 1 , clk $end
$var reg 1 - rst $end
$var reg 1 . add_sub $end
$var reg 29 / x[28:0] $end
$var reg 29 0 y[28:0] $end
$var reg 29 1 z[28:0] $end
$var reg 2 2 is_0[1:0] $end
$var reg 2 3 saturation[1:0] $end
$var reg 29 4 x_reg[28:0] $end
$var reg 29 5 y_reg[28:0] $end
$var reg 29 6 z_reg[28:0] $end
$var reg 1 7 sx $end
$var reg 21 8 fx[20:0] $end
$var reg 7 9 ex[6:0] $end
$var reg 1 : sy $end
$var reg 21 ; fy[20:0] $end
$var reg 7 < ey[6:0] $end
$var reg 1 = sz $end
$var reg 21 > fz[20:0] $end
$var reg 7 ? ez[6:0] $end
$var reg 22 @ fx_ext[21:0] $end
$var reg 22 A fy_ext[21:0] $end
$var reg 149 B aligned_fx[148:0] $end
$var reg 149 C aligned_fy[148:0] $end
$var reg 151 D mx[150:0] $end
$var reg 151 E my[150:0] $end
$var reg 1 F sx_ext $end
$var reg 1 G sy_ext $end
$var reg 151 H mz_pre[150:0] $end
$var reg 151 I mz[150:0] $end
$var reg 151 J mz_shift[150:0] $end
$var reg 21 K fz_pre[20:0] $end
$var reg 21 L fz_aux[20:0] $end
$var reg 8 M abs_exp_diff[7:0] $end
$var integer 32 N aux_index $end
$var integer 32 O shift $end
$var integer 32 P lower_index $end
$var integer 32 Q upper_index $end
$var reg 9 R ex_ext[8:0] $end
$var reg 9 S ey_ext[8:0] $end
$var reg 9 T ez_pre[8:0] $end
$var reg 7 U aux_ez[6:0] $end
$var reg 9 V exp_diff[8:0] $end
$var reg 9 W index[8:0] $end
$scope module regx $end
$var reg 1 X clk $end
$var reg 1 Y rst $end
$var reg 1 Z ena $end
$var reg 29 [ d[28:0] $end
$var reg 29 \ q[28:0] $end
$upscope $end
$scope module regy $end
$var reg 1 ] clk $end
$var reg 1 ^ rst $end
$var reg 1 _ ena $end
$var reg 29 ` d[28:0] $end
$var reg 29 a q[28:0] $end
$upscope $end
$scope module regz $end
$var reg 1 b clk $end
$var reg 1 c rst $end
$var reg 1 d ena $end
$var reg 29 e d[28:0] $end
$var reg 29 f q[28:0] $end
$upscope $end
$upscope $end
$scope module del $end
$var reg 1 g clk $end
$var reg 1 h rst $end
$var reg 29 i a[28:0] $end
$var reg 29 j b[28:0] $end
$comment sr is not handled $end
$upscope $end
$upscope $end
$enddefinitions $end
#0
0!
1"
b00000000000000000000000000000 #
b00000000000000000000000000000 $
b00000000000000000000000000000 %
bUUUUUUUUUUUUUUUUUUUUUUUUUUUUU &
b00000000000000000000000000000 '
b0 (
b0 )
bUUUUUUUUUUUUUUUUUUUUUUUUUUUUU *
1+
0,
1-
1.
b00000000000000000000000000000 /
b00000000000000000000000000000 0
b00000000000000000000000000000 1
b11 2
b11 3
b00000000000000000000000000000 4
b00000000000000000000000000000 5
b00000000000000000000000000000 6
07
b000000000000000000000 8
b0000000 9
0:
b000000000000000000000 ;
b0000000 <
0=
b000000000000000000000 >
b0000000 ?
b1000000000000000000000 @
b1000000000000000000000 A
b00000000000000000000000000000000000000000000000000000000000000000000000000000000000000000000000000000000000000000000000000000001000000000000000000000 B
b00000000000000000000000000000000000000000000000000000000000000000000000000000000000000000000000000000000000000000000000000000001000000000000000000000 C
b0000000000000000000000000000000000000000000000000000000000000000000000000000000000000000000000000000000000000000000000000000000001000000000000000000000 D
b1111111111111111111111111111111111111111111111111111111111111111111111111111111111111111111111111111111111111111111111111111111111000000000000000000000 E
0F
1G
b0000000000000000000000000000000000000000000000000000000000000000000000000000000000000000000000000000000000000000000000000000000000000000000000000000000 H
b0000000000000000000000000000000000000000000000000000000000000000000000000000000000000000000000000000000000000000000000000000000000000000000000000000000 I
b0000000000000000000000000000000000000000000000000000000000000000000000000000000000000000000000000000000000000000000000000000000000000000000000000000000 J
b000000000000000000000 K
b000000000000000000000 L
b00000000 M
b0 N
b11111111111111111111111111101011 O
b0 P
b0 Q
b000000000 R
b000000000 S
b111101011 T
b0000000 U
b000000000 V
b111101011 W
0X
1Y
1Z
b00000000000000000000000000000 [
b00000000000000000000000000000 \
0]
1^
1_
b00000000000000000000000000000 `
b00000000000000000000000000000 a
0b
1c
1d
b00000000000000000000000000000 e
b00000000000000000000000000000 f
0g
0h
b00000000000000000000000000000 i
bUUUUUUUUUUUUUUUUUUUUUUUUUUUUU j
#1000000
0"
0-
0Y
0^
0c
#10000000
1!
b01001001011001000010010101100 #
b01001101001001000111110010010 $
b11001101000011100011101000111 %
b1 (
1,
b01001001011001000010010101100 /
b01001101001001000111110010010 0
1X
b01001001011001000010010101100 [
1]
b01001101001001000111110010010 `
1b
1g
b11001101000011100011101000111 i
#20000000
0!
0,
0X
0]
0b
0g
#30000000
1!
b00011100100111111110011001100 #
b01101000000010110100100101010 $
b11101000000010110100100101001 %
b00000000000000000000000000000 &
b10 (
b00000000000000000000000000000 *
1,
b00011100100111111110011001100 /
b01101000000010110100100101010 0
b00 2
b00 3
b01001001011001000010010101100 4
b01001101001001000111110010010 5
b11001101000011100011101000111 6
b011001000010010101100 8
b1001001 9
b001001000111110010010 ;
b1001101 <
1=
b000011100011101000111 >
b1001101 ?
b1001001000111110010010 @
b1011001000010010101100 A
b00000000000000000000000000000000000000000000000000000000000000000000000000000000000000000000000000000000000000000000000000010010010001111100100100000 B
b00000000000000000000000000000000000000000000000000000000000000000000000000000000000000000000000000000000000000000000000000000001011001000010010101100 C
b1111111111111111111111111111111111111111111111111111111111111111111111111111111111111111111111111111111111111111111111111111101101101110000011011100000 D
b0000000000000000000000000000000000000000000000000000000000000000000000000000000000000000000000000000000000000000000000000000000001011001000010010101100 E
1F
0G
b1111111111111111111111111111111111111111111111111111111111111111111111111111111111111111111111111111111111111111111111111111101111000111000101110001100 H
b0000000000000000000000000000000000000000000000000000000000000000000000000000000000000000000000000000000000000000000000000000010000111000111010001110100 I
b0000111000111010001110100000000000000000000000000000000000000000000000000000000000000000000000000000000000000000000000000000000000000000000000000000000 J
b000011100011101000111 K
b000011100011101000111 L
b00000100 M
b11001 N
b0 O
b100 P
b11000 Q
b001001001 R
b001001101 S
b001001101 T
b1001101 U
b111111100 V
b000000000 W
1X
b00011100100111111110011001100 [
b01001001011001000010010101100 \
1]
b01101000000010110100100101010 `
b01001101001001000111110010010 a
1b
b11001101000011100011101000111 e
1g
b11101000000010110100100101001 i
b00000000000000000000000000000 j
#40000000
0!
0,
0X
0]
0b
0g
#50000000
1!
b10011110001101100110001101110 #
b11000010111011001101011011010 $
b01000010111011001101011011001 %
b11001101000011100011101000111 &
b11001101000011100011101000111 '
b11 (
b11001101000011100011101000111 *
1,
b10011110001101100110001101110 /
b11000010111011001101011011010 0
b11001101000011100011101000111 1
b00011100100111111110011001100 4
b01101000000010110100100101010 5
b11101000000010110100100101001 6
b100111111110011001100 8
b0011100 9
b000010110100100101010 ;
b1101000 <
b000010110100100101001 >
b1101000 ?
b1000010110100100101010 @
b1100111111110011001100 A
b00000000000000000000000000000000000000000000000000010000101101001001010100000000000000000000000000000000000000000000000000000000000000000000000000000 B
b00000000000000000000000000000000000000000000000000000000000000000000000000000000000000000000000000000000000000000000000000000001100111111110011001100 C
b1111111111111111111111111111111111111111111111111111101111010010110110101100000000000000000000000000000000000000000000000000000000000000000000000000000 D
b0000000000000000000000000000000000000000000000000000000000000000000000000000000000000000000000000000000000000000000000000000000001100111111110011001100 E
b1111111111111111111111111111111111111111111111111111101111010010110110101100000000000000000000000000000000000000000000000000000001100111111110011001100 H
b0000000000000000000000000000000000000000000000000000010000101101001001010011111111111111111111111111111111111111111111111111111110011000000001100110100 I
b0000101101001001010011111111111111111111111111111111111111111111111111111110011000000001100110100000000000000000000000000000000000000000000000000000000 J
b000010110100100101001 K
b000010110100100101001 L
b01001100 M
b1100001 N
b0 O
b1001100 P
b1100000 Q
b000011100 R
b001101000 S
b001101000 T
b1101000 U
b110110100 V
b000000000 W
1X
b10011110001101100110001101110 [
b00011100100111111110011001100 \
1]
b11000010111011001101011011010 `
b01101000000010110100100101010 a
1b
b11101000000010110100100101001 e
b11001101000011100011101000111 f
1g
b01000010111011001101011011001 i
b11001101000011100011101000111 j
#60000000
0!
0,
0X
0]
0b
0g
#70000000
1!
b00010100101111001100100110010 #
b01010011011110100000101001000 $
b11010011011110100000101000111 %
b11101000000010110100100101001 &
b11101000000010110100100101001 '
b100 (
b11101000000010110100100101001 *
1,
b00010100101111001100100110010 /
b01010011011110100000101001000 0
b11101000000010110100100101001 1
b10011110001101100110001101110 4
b11000010111011001101011011010 5
b01000010111011001101011011001 6
17
b001101100110001101110 8
b0011110 9
1:
b111011001101011011010 ;
b1000010 <
0=
b111011001101011011001 >
b1000010 ?
b1111011001101011011010 @
b1001101100110001101110 A
b00000000000000000000000000000000000000000000000000000000000000000000000000000000000000000001111011001101011011010000000000000000000000000000000000000 B
b00000000000000000000000000000000000000000000000000000000000000000000000000000000000000000000000000000000000000000000000000000001001101100110001101110 C
b0000000000000000000000000000000000000000000000000000000000000000000000000000000000000000000001111011001101011011010000000000000000000000000000000000000 D
b1111111111111111111111111111111111111111111111111111111111111111111111111111111111111111111111111111111111111111111111111111111110110010011001110010010 E
0F
1G
b0000000000000000000000000000000000000000000000000000000000000000000000000000000000000000000001111011001101011011001111111111111110110010011001110010010 H
b0000000000000000000000000000000000000000000000000000000000000000000000000000000000000000000001111011001101011011001111111111111110110010011001110010010 I
b1110110011010110110011111111111111101100100110011100100100000000000000000000000000000000000000000000000000000000000000000000000000000000000000000000000 J
b111011001101011011001 K
b111011001101011011001 L
b00100100 M
b111001 N
b0 O
b100100 P
b111000 Q
b000011110 R
b001000010 S
b001000010 T
b1000010 U
b111011100 V
b000000000 W
1X
b00010100101111001100100110010 [
b10011110001101100110001101110 \
1]
b01010011011110100000101001000 `
b11000010111011001101011011010 a
1b
b01000010111011001101011011001 e
b11101000000010110100100101001 f
1g
b11010011011110100000101000111 i
b11101000000010110100100101001 j
#80000000
0!
0,
0X
0]
0b
0g
#90000000
1!
b01100001000010111001000011010 #
b00100010001100011001000111100 $
b01100001000010111001000011001 %
b01000010111011001101011011001 &
b01000010111011001101011011001 '
b101 (
b01000010111011001101011011001 *
1,
b01100001000010111001000011010 /
b00100010001100011001000111100 0
b01000010111011001101011011001 1
b00010100101111001100100110010 4
b01010011011110100000101001000 5
b11010011011110100000101000111 6
07
b101111001100100110010 8
b0010100 9
0:
b011110100000101001000 ;
b1010011 <
1=
b011110100000101000111 >
b1010011 ?
b1011110100000101001000 @
b1101111001100100110010 A
b00000000000000000000000000000000000000000000000000000000000000001011110100000101001000000000000000000000000000000000000000000000000000000000000000000 B
b00000000000000000000000000000000000000000000000000000000000000000000000000000000000000000000000000000000000000000000000000000001101111001100100110010 C
b1111111111111111111111111111111111111111111111111111111111111111110100001011111010111000000000000000000000000000000000000000000000000000000000000000000 D
b0000000000000000000000000000000000000000000000000000000000000000000000000000000000000000000000000000000000000000000000000000000001101111001100100110010 E
1F
0G
b1111111111111111111111111111111111111111111111111111111111111111110100001011111010111000000000000000000000000000000000000000000001101111001100100110010 H
b0000000000000000000000000000000000000000000000000000000000000000001011110100000101000111111111111111111111111111111111111111111110010000110011011001110 I
b0111101000001010001111111111111111111111111111111111111111111100100001100110110011100000000000000000000000000000000000000000000000000000000000000000000 J
b011110100000101000111 K
b011110100000101000111 L
b00111111 M
b1010100 N
b0 O
b111111 P
b1010011 Q
b000010100 R
b001010011 S
b001010011 T
b1010011 U
b111000001 V
b000000000 W
1X
b01100001000010111001000011010 [
b00010100101111001100100110010 \
1]
b00100010001100011001000111100 `
b01010011011110100000101001000 a
1b
b11010011011110100000101000111 e
b01000010111011001101011011001 f
1g
b01100001000010111001000011001 i
b01000010111011001101011011001 j
#100000000
0!
0,
0X
0]
0b
0g
#110000000
1!
b00010000111010110111011100010 #
b10101100010000011011000100000 $
b00101100010000011011000100000 %
b11010011011110100000101000111 &
b11010011011110100000101000111 '
b110 (
b11010011011110100000101000111 *
1,
b00010000111010110111011100010 /
b10101100010000011011000100000 0
b11010011011110100000101000111 1
b01100001000010111001000011010 4
b00100010001100011001000111100 5
b01100001000010111001000011001 6
b000010111001000011010 8
b1100001 9
b001100011001000111100 ;
b0100010 <
0=
b000010111001000011001 >
b1100001 ?
b1000010111001000011010 @
b1001100011001000111100 A
b00000000000000000000000000000000000000000000000000000000000000001000010111001000011010000000000000000000000000000000000000000000000000000000000000000 B
b00000000000000000000000000000000000000000000000000000000000000000000000000000000000000000000000000000000000000000000000000000001001100011001000111100 C
b0000000000000000000000000000000000000000000000000000000000000000001000010111001000011010000000000000000000000000000000000000000000000000000000000000000 D
b1111111111111111111111111111111111111111111111111111111111111111111111111111111111111111111111111111111111111111111111111111111110110011100110111000100 E
0F
1G
b0000000000000000000000000000000000000000000000000000000000000000001000010111001000011001111111111111111111111111111111111111111110110011100110111000100 H
b0000000000000000000000000000000000000000000000000000000000000000001000010111001000011001111111111111111111111111111111111111111110110011100110111000100 I
b0000101110010000110011111111111111111111111111111111111111111101100111001101110001000000000000000000000000000000000000000000000000000000000000000000000 J
b000010111001000011001 K
b000010111001000011001 L
b001100001 R
b000100010 S
b001100001 T
b1100001 U
b000111111 V
1X
b00010000111010110111011100010 [
b01100001000010111001000011010 \
1]
b10101100010000011011000100000 `
b00100010001100011001000111100 a
1b
b01100001000010111001000011001 e
b11010011011110100000101000111 f
1g
b00101100010000011011000100000 i
b11010011011110100000101000111 j
#120000000
0!
0,
0X
0]
0b
0g
#130000000
1!
b01000010000100001111010110110 #
b10111101111110100111110001110 $
b01000010001000001100100110010 %
b01100001000010111001000011001 &
b01100001000010111001000011001 '
b111 (
b01100001000010111001000011001 *
1,
b01000010000100001111010110110 /
b10111101111110100111110001110 0
b01100001000010111001000011001 1
b00010000111010110111011100010 4
b10101100010000011011000100000 5
b00101100010000011011000100000 6
b111010110111011100010 8
b0010000 9
1:
b010000011011000100000 ;
b0101100 <
b010000011011000100000 >
b0101100 ?
b1010000011011000100000 @
b1111010110111011100010 A
b00000000000000000000000000000000000000000000000000000000000000000000000000000000000000000000000000010100000110110001000000000000000000000000000000000 B
b00000000000000000000000000000000000000000000000000000000000000000000000000000000000000000000000000000000000000000000000000000001111010110111011100010 C
b0000000000000000000000000000000000000000000000000000000000000000000000000000000000000000000000000000010100000110110001000000000000000000000000000000000 D
b0000000000000000000000000000000000000000000000000000000000000000000000000000000000000000000000000000000000000000000000000000000001111010110111011100010 E
0G
b0000000000000000000000000000000000000000000000000000000000000000000000000000000000000000000000000000010100000110110001000000000001111010110111011100010 H
b0000000000000000000000000000000000000000000000000000000000000000000000000000000000000000000000000000010100000110110001000000000001111010110111011100010 I
b0100000110110001000000000001111010110111011100010000000000000000000000000000000000000000000000000000000000000000000000000000000000000000000000000000000 J
b010000011011000100000 K
b010000011011000100000 L
b00011100 M
b110001 N
b0 O
b11100 P
b110000 Q
b000010000 R
b000101100 S
b000101100 T
b0101100 U
b111100100 V
b000000000 W
1X
b01000010000100001111010110110 [
b00010000111010110111011100010 \
1]
b10111101111110100111110001110 `
b10101100010000011011000100000 a
1b
b00101100010000011011000100000 e
b01100001000010111001000011001 f
1g
b01000010001000001100100110010 i
b01100001000010111001000011001 j
#140000000
0!
0,
0X
0]
0b
0g
