TP2/src/multiplication/delay_gen.vhd
library ieee;
use ieee.std_logic_1164.all;

entity delay_gen is
    generic(
            N: natural:= 26;
            DELAY: natural:= 0
        );
    port(
        clk: in std_logic;
        rst: in std_logic;
        A: in std_logic_vector(N-1 downto 0);
        B: out std_logic_vector(N-1 downto 0)
    );
end;


architecture behavioral of delay_gen is
    type std_logic_matrix is array(DELAY-1 downto 0) of std_logic_vector(N-1 downto 0);   
    signal sr : std_logic_matrix;
begin
    process(clk,rst)
    begin
        if rst='1' then
            sr <= (others=>(others=>'0'));
        elsif clk = '1' and clk'event then
            sr(DELAY-1 downto 1) <= sr(DELAY-2 downto 0);
            sr(0) <= A;
        end if;
    end process;
    B <= sr(DELAY-1);
end;

TP2/src/multiplication/fp_mult_significand.vhd
library IEEE;
use IEEE.std_logic_1164.all;
use IEEE.numeric_std.all;

entity significand is
    generic (
        NF : natural := 21
    );
    port (
        Fx : in std_logic_vector(NF-1 downto 0);
        Fy : in std_logic_vector(NF-1 downto 0);
        is_0 : in std_logic;
        saturation : in std_logic_vector(1 downto 0);
        Fz : out std_logic_vector(NF-1 downto 0);
        add1 : out std_logic
    );
end;


architecture behavioral of significand is
    signal Fx_ext : unsigned(NF downto 0);
    signal Fy_ext : unsigned(NF downto 0);
    signal Fz_ext : unsigned(2*NF+1 downto 0);
    signal Fz_aux : unsigned(NF-1 downto 0);
    signal Fz_pre : unsigned(NF-1 downto 0);
    signal Fz_MSB : std_logic;
    signal aux_sat : std_logic;

    constant ZERO_VALUE : unsigned(NF-1 downto 0) := to_unsigned(0, NF);
    constant SAT_VALUE : unsigned(NF-1 downto 0) := to_unsigned(2**NF -1, NF);

begin

    Fx_ext <= unsigned('1' & Fx);
    Fy_ext <= unsigned('1' & Fy);
    Fz_ext <= Fx_ext * Fy_ext;
    Fz_MSB <= Fz_ext(2*NF+1);
    Fz_aux <= Fz_ext(2*NF downto NF+1) when Fz_MSB='1' else Fz_ext(2*NF-1 downto NF);
    Fz_pre <= Fz_aux when (saturation="10" or saturation="00") else 
              SAT_VALUE when saturation="01" else ZERO_VALUE;

    aux_sat <='0' when (is_0='0') else '1';
    Fz <= std_logic_vector(Fz_pre) when is_0='0' else std_logic_vector(ZERO_VALUE);
    add1 <= Fz_MSB;
end;

TP2/src/multiplication/fp_mult_exponent.vhd
library IEEE;
use IEEE.std_logic_1164.all;
use IEEE.numeric_std.all;

entity exponent is
    generic (
        NE : natural := 7
    );
    port (
        Ex : in std_logic_vector(NE-1 downto 0);
        Ey : in std_logic_vector(NE-1 downto 0);
        is_0 : in std_logic;
        add1 : in std_logic;
        Ez : out std_logic_vector(NE-1 downto 0);
        saturation : out std_logic_vector (1 downto 0)
    );
end;

architecture behavioral of exponent is
    signal Ex_ext : unsigned(NE+1 downto 0);
    signal Ey_ext : unsigned(NE+1 downto 0);
    signal Ez_pre : unsigned(NE+1 downto 0);
    signal aux_add1 : unsigned(NE+1 downto 0);
    signal aux_Ez : unsigned(NE-1 downto 0);

    signal EXC_2C :  unsigned(NE+1 downto 0) := not to_unsigned(2**(NE-1)-1, NE+2) + 1;
    signal OVERFLOW_VALUE : unsigned(NE-1 downto 0) := to_unsigned(2**(NE)-1, NE);
    signal ZERO_VALUE : unsigned(NE-1 downto 0) := to_unsigned(0, NE);

begin
    Ex_ext <= unsigned("00" & Ex);
    Ey_ext <= unsigned("00" & Ey);
    aux_add1 <= to_unsigned(1, NE+2) when add1='1' else to_unsigned(0, NE+2);
    Ez_pre <= Ex_ext + Ey_ext + EXC_2C + aux_add1;
    saturation <= std_logic_vector(Ez_pre(NE+1 downto NE));
    aux_Ez <= Ez_pre(NE-1 downto 0) when Ez_pre(NE+1 downto NE)="00" else 
              OVERFLOW_VALUE when Ez_pre(NE+1 downto NE)="01" else ZERO_VALUE;
    Ez <= std_logic_vector(aux_Ez) when is_0='0' else std_logic_vector(ZERO_VALUE);
end;

TP2/src/adder/register.vhd
library IEEE;
use IEEE.std_logic_1164.all;

entity reg is
    generic(N: integer := 4);
    port (
        clk : in std_logic;
        rst : in std_logic;
        ena : in std_logic;
        D : in std_logic_vector(N-1 downto 0);
        Q : out std_logic_vector(N-1 downto 0)
    );
end;

architecture behavioral of reg is
begin
    process(clk, rst)
    begin
        if rst='1' then
            Q <= (others => '0');
        elsif rising_edge(clk) then
            if ena='1' then
                Q <= D;
            end if;
        end if;
    end process;
end;

TP2/src/multiplication/fp_multiplication.vhd
library IEEE;
use IEEE.std_logic_1164.all;
use IEEE.numeric_std.all;

entity fp_multiplication is
    generic (
        NE : natural := 7;
        NF : natural := 21
    );
    port (
        clk : in std_logic;
        rst : in std_logic;
        x : in std_logic_vector(NF+NE downto 0);
        y : in std_logic_vector(NF+NE downto 0);
        z : out std_logic_vector(NF+NE downto 0)
    );
end;

architecture behavioral of fp_multiplication is
    signal is_0 : std_logic;
    signal sign : std_logic;
    signal add_1 : std_logic;
    signal saturation : std_logic_vector(1 downto 0);

    signal x_reg : std_logic_vector(NF+NE downto 0);
    signal y_reg : std_logic_vector(NF+NE downto 0);
    signal z_reg : std_logic_vector(NF+NE downto 0);

begin

    regX: entity work.reg(behavioral)
        generic map(NF+NE+1)
        port map(
            clk => clk,
            rst => rst,
            ena => '1',
            D => x,
            Q => x_reg
        );

    regY: entity work.reg(behavioral)
        generic map (NF+NE+1)
        port map (
            clk => clk,
            rst => rst,
            ena => '1',
            D => y,
            Q => y_reg
        );

    regZ: entity work.reg(behavioral)
        generic map (NF+NE+1)
        port map (
            clk => clk,
            rst => rst,
            ena => '1',
            D => z_reg,
            Q => z
        );

    IS_0_INST : is_0 <= '1' when (unsigned(x_reg(NF+NE-1 downto 0))=0 OR unsigned(y_reg(NF+NE-1 downto 0))=0)
                        else '0';

    SIGN_INST : sign <= x_reg(NF+NE) XOR y_reg(NF+NE);

    EXP_INST : entity work.exponent(behavioral)
                generic map (
                    NE => NE
                )
                port map (
                    Ex => x_reg(NF+NE-1 downto NF),
                    Ey => y_reg(NF+NE-1 downto NF),
                    is_0 => is_0,
                    add1 => add_1,
                    Ez => z_reg(NF+NE-1 downto NF),
                    saturation => saturation
                );
    
    SIG_INST : entity work.significand(behavioral)
                generic map (
                    NF => NF
                )
                port map (
                    Fx => x_reg(NF-1 downto 0),
                    Fy => y_reg(NF-1 downto 0),
                    is_0 => is_0,
                    saturation => saturation,
                    Fz => z_reg(NF-1 downto 0),
                    add1 => add_1
                );
    
    Z_sign_inst: z_reg(NF+NE) <= sign; 
end;

TP2/src/multiplication/testbench_mult.vhd
library ieee;
use ieee.std_logic_1164.all;
use ieee.numeric_std.all;
use std.textio.all;


entity pf_testbench is
end entity pf_testbench;


architecture pf_testbench_arq of pf_testbench is
    constant TCK: time:= 20 ns; -- periodo de reloj
    constant DELAY: natural:= 2; -- retardo de procesamiento del DUV
    constant NF : natural := 21;
    constant EXP_SIZE_T: natural:= 7; -- tamanio exponente
    constant WORD_SIZE_T: natural:= NF+EXP_SIZE_T+1; -- tamanio de datos
    signal clk: std_logic:= '0';
    signal rst: std_logic:= '1';
    signal a_file: unsigned(WORD_SIZE_T-1 downto 0):= (others => '0');
    signal b_file: unsigned(WORD_SIZE_T-1 downto 0):= (others => '0');
    signal z_file: unsigned(WORD_SIZE_T-1 downto 0):= (others => '0');
    signal z_del: unsigned(WORD_SIZE_T-1 downto 0):= (others => '0'); 
    signal z_duv: std_logic_vector(WORD_SIZE_T-1 downto 0):= (others => '0');
    signal ciclos: integer := 0; signal errores: integer := 0;
    -- La senal z_del_aux se define por un problema de conversion
    signal z_del_aux: std_logic_vector(WORD_SIZE_T-1 downto 0):= (others => '0');

    file datos: text open read_mode is "../testbench/fmul_21_7.txt";
    -- Declaracion del componente a probar
    component fp_multiplication is
        generic(
                NE: natural := 7;
                NF: natural := 21
            );
            port(
                clk : in std_logic;
                rst : in std_logic;
                x : in std_logic_vector(NF+NE downto 0);
                y : in std_logic_vector(NF+NE downto 0);
                z : out std_logic_vector(NF+NE downto 0)
                );
    end component fp_multiplication ;
    -- Declaracion de la linea de retardo
    component delay_gen is
        generic(
            N: natural:= 26;
            DELAY: natural:= 0
        );
        port(
            clk: in std_logic;
            rst: in std_logic;
            A: in std_logic_vector(N-1 downto 0);
            B: out std_logic_vector(N-1 downto 0)
        );
    end component;
begin
    -- Generacion del clock del sistema
    clk <= not(clk) after TCK/ 2; -- reloj
    rst <= '0' after 1 ns;

    Test_Sequence: process
        variable l: line;

        variable ch: character:= ' ';
        variable aux: integer;
    begin
        while not(endfile(datos)) loop
            wait until rising_edge(clk);
            -- solo para debugging
            ciclos <= ciclos + 1;
            -- se lee una linea del archivo de valores de prueba
            readline(datos, l);
            -- se extrae un entero de la linea
            read(l, aux);
            -- se carga el valor del operando A
            a_file <= to_unsigned(aux, WORD_SIZE_T);
            -- se lee un caracter (es el espacio)
            read(l, ch);
            -- se lee otro entero de la linea
            read(l, aux);
            -- se carga el valor del operando B
            b_file <= to_unsigned(aux, WORD_SIZE_T);
            -- se lee otro caracter (es el espacio)
            read(l, ch);
            -- se lee otro entero
            read(l, aux);
            -- se carga el valor de salida (resultado)
            z_file <= to_unsigned(aux, WORD_SIZE_T);
        end loop;
        -- se cierra del archivo
        file_close(datos);
        wait for TCK*(DELAY+1);
        -- se aborta la simulacion (fin del archivo)
        assert false report
        "Fin de la simulacion" severity failure;
    end process Test_Sequence;
-- Instanciacion del DUV
DUV: fp_multiplication 
        generic map (
                NE => EXP_SIZE_T,
                NF => NF
        )
        port map(
            clk => clk,
            rst => rst,
            x => std_logic_vector(a_file),
            y => std_logic_vector(b_file),
            z => z_duv
        );
-- Instanciacion de la linea de retardo
del: delay_gen
    generic map(WORD_SIZE_T, DELAY)
    port map(clk, '0', std_logic_vector(z_file), z_del_aux);
    z_del <= unsigned(z_del_aux);
-- Verificacion de la condicion
verificacion: process(clk)
        begin
            if rising_edge(clk) then
            assert to_integer(z_del) = to_integer(unsigned(z_duv)) report
            "Error: Salida del DUV no coincide con referencia (salida del duv = " &
            integer'image(to_integer(unsigned(z_duv))) & ", salida del archivo = " &
            integer'image(to_integer(z_del)) & ")" &
            "Errores= " & integer'image(errores+1) & " en la linea " & integer'image(ciclos-2)
            severity warning;
            if to_integer(z_del) /= to_integer(unsigned(z_duv)) then
            errores <= errores + 1;
            end if;
            end if;
        end process;
end architecture pf_testbench_arq;

TP2/sym/pf_testbench.vcd
$date
  Fri Nov 10 14:29:54 2023
$end
$version
  GHDL v0
$end
$timescale
  1 fs
$end
$scope module standard $end
$upscope $end
$scope module std_logic_1164 $end
$upscope $end
$scope module numeric_std $end
$upscope $end
$scope module textio $end
$upscope $end
$scope module pf_testbench $end
$var reg 1 ! clk $end
$var reg 1 " rst $end
$var reg 29 # a_file[28:0] $end
$var reg 29 $ b_file[28:0] $end
$var reg 29 % z_file[28:0] $end
$var reg 29 & z_del[28:0] $end
$var reg 29 ' z_duv[28:0] $end
$var integer 32 ( ciclos $end
$var integer 32 ) errores $end
$var reg 29 * z_del_aux[28:0] $end
$scope module duv $end
$var reg 1 + clk $end
$var reg 1 , rst $end
$var reg 29 - x[28:0] $end
$var reg 29 . y[28:0] $end
$var reg 29 / z[28:0] $end
$var reg 1 0 is_0 $end
$var reg 1 1 sign $end
$var reg 1 2 add_1 $end
$var reg 2 3 saturation[1:0] $end
$var reg 29 4 x_reg[28:0] $end
$var reg 29 5 y_reg[28:0] $end
$var reg 29 6 z_reg[28:0] $end
$scope module regx $end
$var reg 1 7 clk $end
$var reg 1 8 rst $end
$var reg 1 9 ena $end
$var reg 29 : d[28:0] $end
$var reg 29 ; q[28:0] $end
$upscope $end
$scope module regy $end
$var reg 1 < clk $end
$var reg 1 = rst $end
$var reg 1 > ena $end
$var reg 29 ? d[28:0] $end
$var reg 29 @ q[28:0] $end
$upscope $end
$scope module regz $end
$var reg 1 A clk $end
$var reg 1 B rst $end
$var reg 1 C ena $end
$var reg 29 D d[28:0] $end
$var reg 29 E q[28:0] $end
$upscope $end
$scope module exp_inst $end
$var reg 7 F ex[6:0] $end
$var reg 7 G ey[6:0] $end
$var reg 1 H is_0 $end
$var reg 1 I add1 $end
$var reg 7 J ez[6:0] $end
$var reg 2 K saturation[1:0] $end
$var reg 9 L ex_ext[8:0] $end
$var reg 9 M ey_ext[8:0] $end
$var reg 9 N ez_pre[8:0] $end
$var reg 9 O aux_add1[8:0] $end
$var reg 7 P aux_ez[6:0] $end
$var reg 9 Q exc_2c[8:0] $end
$var reg 7 R overflow_value[6:0] $end
$var reg 7 S zero_value[6:0] $end
$upscope $end
$scope module sig_inst $end
$var reg 21 T fx[20:0] $end
$var reg 21 U fy[20:0] $end
$var reg 1 V is_0 $end
$var reg 2 W saturation[1:0] $end
$var reg 21 X fz[20:0] $end
$var reg 1 Y add1 $end
$var reg 22 Z fx_ext[21:0] $end
$var reg 22 [ fy_ext[21:0] $end
$var reg 44 \ fz_ext[43:0] $end
$var reg 21 ] fz_aux[20:0] $end
$var reg 21 ^ fz_pre[20:0] $end
$var reg 1 _ fz_msb $end
$var reg 1 ` aux_sat $end
$upscope $end
$upscope $end
$scope module del $end
$var reg 1 a clk $end
$var reg 1 b rst $end
$var reg 29 c a[28:0] $end
$var reg 29 d b[28:0] $end
$comment sr is not handled $end
$upscope $end
$upscope $end
$enddefinitions $end
#0
0!
1"
b00000000000000000000000000000 #
b00000000000000000000000000000 $
b00000000000000000000000000000 %
bUUUUUUUUUUUUUUUUUUUUUUUUUUUUU &
b00000000000000000000000000000 '
b0 (
b0 )
bUUUUUUUUUUUUUUUUUUUUUUUUUUUUU *
0+
1,
b00000000000000000000000000000 -
b00000000000000000000000000000 .
b00000000000000000000000000000 /
10
01
02
b11 3
b00000000000000000000000000000 4
b00000000000000000000000000000 5
b00000000000000000000000000000 6
07
18
19
b00000000000000000000000000000 :
b00000000000000000000000000000 ;
0<
1=
1>
b00000000000000000000000000000 ?
b00000000000000000000000000000 @
0A
1B
1C
b00000000000000000000000000000 D
b00000000000000000000000000000 E
b0000000 F
b0000000 G
1H
0I
b0000000 J
b11 K
b000000000 L
b000000000 M
b111000001 N
b000000000 O
b0000000 P
b111000001 Q
b1111110 R
b0000000 S
b000000000000000000000 T
b000000000000000000000 U
1V
b11 W
b000000000000000000000 X
0Y
b1000000000000000000000 Z
b1000000000000000000000 [
b01000000000000000000000000000000000000000000 \
b000000000000000000000 ]
b000000000000000000000 ^
0_
1`
0a
0b
b00000000000000000000000000000 c
bUUUUUUUUUUUUUUUUUUUUUUUUUUUUU d
#1000000
0"
0,
08
0=
0B
#10000000
1!
b00000111110110100100000111010 #
b01010001111000011111011100100 $
b00011010101111100110111110111 %
b1 (
1+
b00000111110110100100000111010 -
b01010001111000011111011100100 .
17
b00000111110110100100000111010 :
1<
b01010001111000011111011100100 ?
1A
1a
b00011010101111100110111110111 c
#20000000
0!
0+
07
0<
0A
0a
#30000000
1!
b00100001111111010111011000000 #
b10111100110010000001100011100 $
b10011111110001011101010111011 %
b00000000000000000000000000000 &
b10 (
b00000000000000000000000000000 *
1+
b00100001111111010111011000000 -
b10111100110010000001100011100 .
00
12
b00 3
b00000111110110100100000111010 4
b01010001111000011111011100100 5
b00011010101111100110111110111 6
17
b00100001111111010111011000000 :
b00000111110110100100000111010 ;
1<
b10111100110010000001100011100 ?
b01010001111000011111011100100 @
1A
b00011010101111100110111110111 D
b0000111 F
b1010001 G
0H
1I
b0011010 J
b00 K
b000000111 L
b001010001 M
b000011010 N
b000000001 O
b0011010 P
b110110100100000111010 T
b111000011111011100100 U
0V
b00 W
b101111100110111110111 X
1Y
b1110110100100000111010 Z
b1111000011111011100100 [
b11011111001101111101111000100101111110101000 \
b101111100110111110111 ]
b101111100110111110111 ^
1_
0`
1a
b10011111110001011101010111011 c
b00000000000000000000000000000 d
#40000000
0!
0+
07
0<
0A
0a
#50000000
1!
b11101010011111000001100110010 #
b11100110101010001010010110110 $
b01111110111111111111111111111 %
b00011010101111100110111110111 &
b00011010101111100110111110111 '
b11 (
b00011010101111100110111110111 *
1+
b11101010011111000001100110010 -
b11100110101010001010010110110 .
b00011010101111100110111110111 /
11
b00100001111111010111011000000 4
b10111100110010000001100011100 5
b10011111110001011101010111011 6
17
b11101010011111000001100110010 :
b00100001111111010111011000000 ;
1<
b11100110101010001010010110110 ?
b10111100110010000001100011100 @
1A
b10011111110001011101010111011 D
b00011010101111100110111110111 E
b0100001 F
b0111100 G
b0011111 J
b000100001 L
b000111100 M
b000011111 N
b0011111 P
b111111010111011000000 T
b110010000001100011100 U
b110001011101010111011 X
b1111111010111011000000 Z
b1110010000001100011100 [
b11100010111010101110110000110101110100000000 \
b110001011101010111011 ]
b110001011101010111011 ^
1a
b01111110111111111111111111111 c
b00011010101111100110111110111 d
#60000000
0!
0+
07
0<
0A
0a
#70000000
1!
b01000010010111000110111011010 #
b10111011001011010010010110000 $
b10111110100110011110000101010 %
b10011111110001011101010111011 &
b10011111110001011101010111011 '
b100 (
b10011111110001011101010111011 *
1+
b01000010010111000110111011010 -
b10111011001011010010010110000 .
b10011111110001011101010111011 /
01
b01 3
b11101010011111000001100110010 4
b11100110101010001010010110110 5
b01111110111111111111111111111 6
17
b01000010010111000110111011010 :
b11101010011111000001100110010 ;
1<
b10111011001011010010010110000 ?
b11100110101010001010010110110 @
1A
b01111110111111111111111111111 D
b10011111110001011101010111011 E
b1101010 F
b1100110 G
b1111110 J
b01 K
b001101010 L
b001100110 M
b010010010 N
b1111110 P
b011111000001100110010 T
b101010001010010110110 U
b01 W
b111111111111111111111 X
b1011111000001100110010 Z
b1101010001010010110110 [
b10011101101000000001011000010010110110001100 \
b001110110100000000101 ]
b111111111111111111111 ^
1a
b10111110100110011110000101010 c
b10011111110001011101010111011 d
#80000000
0!
0+
07
0<
0A
0a
#90000000
1!
b11011100101110001010100111100 #
b11110010001001011100011101000 $
b01111110111111111111111111111 %
b01111110111111111111111111111 &
b01111110111111111111111111111 '
b101 (
b01111110111111111111111111111 *
1+
b11011100101110001010100111100 -
b11110010001001011100011101000 .
b01111110111111111111111111111 /
11
02
b00 3
b01000010010111000110111011010 4
b10111011001011010010010110000 5
b10111110100110011110000101010 6
17
b11011100101110001010100111100 :
b01000010010111000110111011010 ;
1<
b11110010001001011100011101000 ?
b10111011001011010010010110000 @
1A
b10111110100110011110000101010 D
b01111110111111111111111111111 E
b1000010 F
b0111011 G
0I
b0111110 J
b00 K
b001000010 L
b000111011 M
b000111110 N
b000000000 O
b0111110 P
b010111000110111011010 T
b001011010010010110000 U
b00 W
b100110011110000101010 X
0Y
b1010111000110111011010 Z
b1001011010010010110000 [
b01100110011110000101010100110010110111100000 \
b100110011110000101010 ]
b100110011110000101010 ^
0_
1a
b01111110111111111111111111111 c
b01111110111111111111111111111 d
#100000000
0!
0+
07
0<
0A
0a
#110000000
1!
b00011110101100011101010101100 #
b00001100111010100010011000100 $
b00000000000000000000000000000 %
b10111110100110011110000101010 &
b10111110100110011110000101010 '
b110 (
b10111110100110011110000101010 *
1+
b00011110101100011101010101100 -
b00001100111010100010011000100 .
b10111110100110011110000101010 /
01
b01 3
b11011100101110001010100111100 4
b11110010001001011100011101000 5
b01111110111111111111111111111 6
17
b00011110101100011101010101100 :
b11011100101110001010100111100 ;
1<
b00001100111010100010011000100 ?
b11110010001001011100011101000 @
1A
b01111110111111111111111111111 D
b10111110100110011110000101010 E
b1011100 F
b1110010 G
b1111110 J
b01 K
b001011100 L
b001110010 M
b010001111 N
b1111110 P
b101110001010100111100 T
b001001011100011101000 U
b01 W
b111111111111111111111 X
b1101110001010100111100 Z
b1001001011100011101000 [
b01111110011011000101100111100101111001100000 \
b111110011011000101100 ]
b111111111111111111111 ^
1a
b00000000000000000000000000000 c
b10111110100110011110000101010 d
#120000000
0!
0+
07
0<
0A
0a
#130000000
1!
b10010100111111110100001110010 #
b00010010111001011111000110100 $
b10000000000000000000000000000 %
b01111110111111111111111111111 &
b01111110111111111111111111111 '
b111 (
b01111110111111111111111111111 *
1+
b10010100111111110100001110010 -
b00010010111001011111000110100 .
b01111110111111111111111111111 /
12
b11 3
b00011110101100011101010101100 4
b00001100111010100010011000100 5
b00000000000000000000000000000 6
17
b10010100111111110100001110010 :
b00011110101100011101010101100 ;
1<
b00010010111001011111000110100 ?
b00001100111010100010011000100 @
1A
b00000000000000000000000000000 D
b01111110111111111111111111111 E
b0011110 F
b0001100 G
1I
b0000000 J
b11 K
b000011110 L
b000001100 M
b111101100 N
b000000001 O
b0000000 P
b101100011101010101100 T
b111010100010011000100 U
b11 W
b000000000000000000000 X
1Y
b1101100011101010101100 Z
b1111010100010011000100 [
b11001111101010001100000101101001101110110000 \
b100111110101000110000 ]
b000000000000000000000 ^
1_
1a
b10000000000000000000000000000 c
b01111110111111111111111111111 d
#140000000
0!
0+
07
0<
0A
0a
#150000000
1!
b01111000111110010001101011110 #
b00110110110111101101010111010 $
b01110000110110000110001100010 %
b00000000000000000000000000000 &
b00000000000000000000000000000 '
b1000 (
b00000000000000000000000000000 *
1+
b01111000111110010001101011110 -
b00110110110111101101010111010 .
b00000000000000000000000000000 /
11
b10010100111111110100001110010 4
b00010010111001011111000110100 5
b10000000000000000000000000000 6
17
b01111000111110010001101011110 :
b10010100111111110100001110010 ;
1<
b00110110110111101101010111010 ?
b00010010111001011111000110100 @
1A
b10000000000000000000000000000 D
b00000000000000000000000000000 E
b0010100 F
b0010010 G
b000010100 L
b000010010 M
b111101000 N
b111111110100001110010 T
b111001011111000110100 U
b1111111110100001110010 Z
b1111001011111000110100 [
b11110010100111110110001101111101001100101000 \
b111001010011111011000 ]
1a
b01110000110110000110001100010 c
b00000000000000000000000000000 d
#160000000
0!
0+
07
0<
0A
0a
#170000000
1!
b00110010101101111101001011110 #
b10000100000101101011101111100 $
b10000000000000000000000000000 %
b10000000000000000000000000000 &
b10000000000000000000000000000 '
b1001 (
b10000000000000000000000000000 *
1+
b00110010101101111101001011110 -
b10000100000101101011101111100 .
b10000000000000000000000000000 /
01
b00 3
b01111000111110010001101011110 4
b00110110110111101101010111010 5
b01110000110110000110001100010 6
17
b00110010101101111101001011110 :
b01111000111110010001101011110 ;
1<
b10000100000101101011101111100 ?
b00110110110111101101010111010 @
1A
b01110000110110000110001100010 D
b10000000000000000000000000000 E
b1111000 F
b0110110 G
b1110000 J
b00 K
b001111000 L
b000110110 M
b001110000 N
b1110000 P
b111110010001101011110 T
b110111101101010111010 U
b00 W
b110110000110001100010 X
b1111110010001101011110 Z
b1110111101101010111010 [
b11101100001100011000101001111011111001001100 \
b110110000110001100010 ]
b110110000110001100010 ^
1a
b10000000000000000000000000000 c
b10000000000000000000000000000 d
#180000000
0!
0+
07
0<
0A
0a
#190000000
1!
b10011111101001001110101000010 #
b10110111111001100001001001110 $
b00011000100011111001100101010 %
b01110000110110000110001100010 &
b01110000110110000110001100010 '
b1010 (
b01110000110110000110001100010 *
1+
b10011111101001001110101000010 -
b10110111111001100001001001110 .
b01110000110110000110001100010 /
11
02
b11 3
b00110010101101111101001011110 4
b10000100000101101011101111100 5
b10000000000000000000000000000 6
17
b10011111101001001110101000010 :
b00110010101101111101001011110 ;
1<
b10110111111001100001001001110 ?
b10000100000101101011101111100 @
1A
b10000000000000000000000000000 D
b01110000110110000110001100010 E
b0110010 F
b0000100 G
0I
b0000000 J
b11 K
b000110010 L
b000000100 M
b111110111 N
b000000000 O
b0000000 P
b101101111101001011110 T
b000101101011101111100 U
b11 W
b000000000000000000000 X
0Y
b1101101111101001011110 Z
b1000101101011101111100 [
b01110111101110000111011000100011011110001000 \
b110111101110000111011 ]
b000000000000000000000 ^
0_
1a
b00011000100011111001100101010 c
b01110000110110000110001100010 d
#200000000
0!
0+
07
0<
0A
0a
#210000000
1!
b11110100110101110000100000110 #
b00010001000100000110110101110 $
b11000110111101010100001000001 %
b10000000000000000000000000000 &
b10000000000000000000000000000 '
b1011 (
b10000000000000000000000000000 *
1+
b11110100110101110000100000110 -
b00010001000100000110110101110 .
b10000000000000000000000000000 /
01
12
b00 3
b10011111101001001110101000010 4
b10110111111001100001001001110 5
b00011000100011111001100101010 6
17
b11110100110101110000100000110 :
b10011111101001001110101000010 ;
1<
b00010001000100000110110101110 ?
b10110111111001100001001001110 @
1A
b00011000100011111001100101010 D
b10000000000000000000000000000 E
b0011111 F
b0110111 G
1I
b0011000 J
b00 K
b000011111 L
b000110111 M
b000011000 N
b000000001 O
b0011000 P
b101001001110101000010 T
b111001100001001001110 U
b00 W
b100011111001100101010 X
1Y
b1101001001110101000010 Z
b1111001100001001001110 [
b11000111110011001010101010111110111000011100 \
b100011111001100101010 ]
b100011111001100101010 ^
1_
1a
b11000110111101010100001000001 c
b10000000000000000000000000000 d
#220000000
0!
0+
07
0<
0A
0a
#230000000
1!
b10100100000100011101000000100 #
b11011011010011011101111100010 $
b01000000011001010001101001001 %
b00011000100011111001100101010 &
b00011000100011111001100101010 '
b1100 (
b00011000100011111001100101010 *
1+
b10100100000100011101000000100 -
b11011011010011011101111100010 .
b00011000100011111001100101010 /
11
02
b11110100110101110000100000110 4
b00010001000100000110110101110 5
b11000110111101010100001000001 6
17
b10100100000100011101000000100 :
b11110100110101110000100000110 ;
1<
b11011011010011011101111100010 ?
b00010001000100000110110101110 @
1A
b11000110111101010100001000001 D
b00011000100011111001100101010 E
b1110100 F
b0010001 G
0I
b1000110 J
b001110100 L
b000010001 M
b001000110 N
b000000000 O
b1000110 P
b110101110000100000110 T
b000100000110110101110 U
b111101010100001000001 X
0Y
b1110101110000100000110 Z
b1000100000110110101110 [
b01111101010100001000001111100100000000010100 \
b111101010100001000001 ]
b111101010100001000001 ^
0_
1a
b01000000011001010001101001001 c
b00011000100011111001100101010 d
#240000000
0!
0+
07
0<
0A
0a
#250000000
1!
b01011001000010001101001000000 #
b10011000001110011101101110100 $
b10110010010001001010101111110 %
b11000110111101010100001000001 &
b11000110111101010100001000001 '
b1101 (
b11000110111101010100001000001 *
1+
b01011001000010001101001000000 -
b10011000001110011101101110100 .
b11000110111101010100001000001 /
01
b10100100000100011101000000100 4
b11011011010011011101111100010 5
b01000000011001010001101001001 6
17
b01011001000010001101001000000 :
b10100100000100011101000000100 ;
1<
b10011000001110011101101110100 ?
b11011011010011011101111100010 @
1A
b01000000011001010001101001001 D
b11000110111101010100001000001 E
b0100100 F
b1011011 G
b1000000 J
b000100100 L
b001011011 M
b001000000 N
b1000000 P
b000100011101000000100 T
b010011011101111100010 U
b011001010001101001001 X
b1000100011101000000100 Z
b1010011011101111100010 [
b01011001010001101001001111000010001110001000 \
b011001010001101001001 ]
b011001010001101001001 ^
1a
b10110010010001001010101111110 c
b11000110111101010100001000001 d
#260000000
0!
0+
07
0<
0A
0a
#270000000
1!
b10101101000011011010001110110 #
b01001010111111000000100110100 $
b10111001000010111000110101111 %
b01000000011001010001101001001 &
b01000000011001010001101001001 '
b1110 (
b01000000011001010001101001001 *
1+
b10101101000011011010001110110 -
b01001010111111000000100110100 .
b01000000011001010001101001001 /
11
b01011001000010001101001000000 4
b10011000001110011101101110100 5
b10110010010001001010101111110 6
17
b10101101000011011010001110110 :
b01011001000010001101001000000 ;
1<
b01001010111111000000100110100 ?
b10011000001110011101101110100 @
1A
b10110010010001001010101111110 D
b01000000011001010001101001001 E
b1011001 F
b0011000 G
b0110010 J
b001011001 L
b000011000 M
b000110010 N
b0110010 P
b000010001101001000000 T
b001110011101101110100 U
b010001001010101111110 X
b1000010001101001000000 Z
b1001110011101101110100 [
b01010001001010101111110011001010010100000000 \
b010001001010101111110 ]
b010001001010101111110 ^
1a
b10111001000010111000110101111 c
b01000000011001010001101001001 d
#280000000
0!
0+
07
0<
0A
0a
#290000000
1!
b10100011011000111110010100000 #
b11001010001111000111011111010 $
b00101110101101111111010100111 %
b10110010010001001010101111110 &
b10110010010001001010101111110 '
b1111 (
b10110010010001001010101111110 *
1+
b10100011011000111110010100000 -
b11001010001111000111011111010 .
b10110010010001001010101111110 /
12
b10101101000011011010001110110 4
b01001010111111000000100110100 5
b10111001000010111000110101111 6
17
b10100011011000111110010100000 :
b10101101000011011010001110110 ;
1<
b11001010001111000111011111010 ?
b01001010111111000000100110100 @
1A
b10111001000010111000110101111 D
b10110010010001001010101111110 E
b0101101 F
b1001010 G
1I
b0111001 J
b000101101 L
b001001010 M
b000111001 N
b000000001 O
b0111001 P
b000011011010001110110 T
b111111000000100110100 U
b000010111000110101111 X
1Y
b1000011011010001110110 Z
b1111111000000100110100 [
b10000101110001101011110100100001110111111000 \
b000010111000110101111 ]
b000010111000110101111 ^
1_
1a
b00101110101101111111010100111 c
b10110010010001001010101111110 d
#300000000
0!
0+
07
0<
0A
0a
#310000000
1!
b00000111000100101011111111110 #
b10100001011001101100101101010 $
b10000000000000000000000000000 %
b10111001000010111000110101111 &
b10111001000010111000110101111 '
b10000 (
b10111001000010111000110101111 *
1+
b00000111000100101011111111110 -
b10100001011001101100101101010 .
b10111001000010111000110101111 /
01
02
b10100011011000111110010100000 4
b11001010001111000111011111010 5
b00101110101101111111010100111 6
17
b00000111000100101011111111110 :
b10100011011000111110010100000 ;
1<
b10100001011001101100101101010 ?
b11001010001111000111011111010 @
1A
b00101110101101111111010100111 D
b10111001000010111000110101111 E
b0100011 F
0I
b0101110 J
b000100011 L
b000101110 N
b000000000 O
b0101110 P
b011000111110010100000 T
b001111000111011111010 U
b101101111111010100111 X
0Y
b1011000111110010100000 Z
b1001111000111011111010 [
b01101101111111010100111100100111010001000000 \
b101101111111010100111 ]
b101101111111010100111 ^
0_
1a
b10000000000000000000000000000 c
b10111001000010111000110101111 d
#320000000
0!
0+
07
0<
0A
0a
